spongecase/__init__.py
spongecase/__main__.py
spongecase/__version__.py
spongecase-1.0.3.dist-info/LICENSE.txt
spongecase-1.0.3.dist-info/METADATA
spongecase-1.0.3.dist-info/WHEEL
spongecase-1.0.3.dist-info/entry_points.txt
spongecase-1.0.3.dist-info/top_level.txt
spongecase-1.0.3.dist-info/RECORD
