Metadata-Version: 2.1
Name: spongecase
Version: 1.0.3
Summary: Convert text to Spongebob case
Home-page: https://github.com/nkouevda/spongecase
Author: Nikita Kouevda
Author-email: nkouevda@gmail.com
License: MIT
License-File: LICENSE.txt
